{
  "meta": {
    "version": "0.1",
    "timestamp": "2025-03-11T18:20:50.455547",
    "save_name": "Rusty Rocket"
  },
  "player": {
    "position": {
      "x": 323,
      "y": 261
    },
    "health": 100,
    "max_health": 100,
    "credits": 0
  },
  "current_location": {
    "id": "rusty_rocket",
    "docked_location": null
  },
  "ship": {
    "hull_strength": 56,
    "shield_strength": 5.5,
    "thrust_power": 0.12100000000000001,
    "rotation_speed": 3.3000000000000003,
    "max_speed": 4.95
  },
  "inventory": {
    "credits": 0,
    "items": []
  },
  "game_flags": {
    "tutorial_completed": false
  },
  "visited_locations": [
    "psyche_township"
  ],
  "resources": {
    "metal": 0,
    "crystal": 0,
    "fuel": 0
  }
}